{
    "version": "5.4.1",
    "flags": {},
    "shapes": [
        {
            "label": "osteochondroma",
            "points": [
                [
                    88,
                    65
                ],
                [
                    94,
                    82
                ]
            ],
            "group_id": null,
            "description": "",
            "shape_type": "rectangle",
            "flags": {},
            "mask": null
        },
        {
            "label": "osteochondroma",
            "points": [
                [
                    94,
                    65
                ],
                [
                    93,
                    81
                ],
                [
                    91,
                    82
                ],
                [
                    89,
                    78
                ],
                [
                    89,
                    77
                ],
                [
                    90,
                    75
                ],
                [
                    89,
                    73
                ],
                [
                    88,
                    72
                ],
                [
                    89,
                    66
                ],
                [
                    90,
                    66
                ],
                [
                    92,
                    66
                ]
            ],
            "group_id": null,
            "description": "",
            "shape_type": "polygon",
            "flags": {},
            "mask": null
        }
    ],
    "imagePath": "IMG001117.jpg",
    "imageData": null,
    "imageHeight": 224,
    "imageWidth": 224
}