{
    "version": "5.4.1",
    "flags": {},
    "shapes": [
        {
            "label": "osteochondroma",
            "points": [
                [
                    29,
                    55
                ],
                [
                    48,
                    88
                ]
            ],
            "group_id": null,
            "description": "",
            "shape_type": "rectangle",
            "flags": {},
            "mask": null
        },
        {
            "label": "osteochondroma",
            "points": [
                [
                    32,
                    55
                ],
                [
                    35,
                    55
                ],
                [
                    36,
                    56
                ],
                [
                    38,
                    57
                ],
                [
                    39,
                    59
                ],
                [
                    41,
                    63
                ],
                [
                    41,
                    67
                ],
                [
                    43,
                    72
                ],
                [
                    44,
                    77
                ],
                [
                    45,
                    78
                ],
                [
                    47,
                    79
                ],
                [
                    47,
                    79
                ],
                [
                    48,
                    81
                ],
                [
                    48,
                    82
                ],
                [
                    47,
                    82
                ],
                [
                    46,
                    83
                ],
                [
                    44,
                    84
                ],
                [
                    44,
                    85
                ],
                [
                    44,
                    86
                ],
                [
                    44,
                    87
                ],
                [
                    42,
                    88
                ],
                [
                    40,
                    87
                ],
                [
                    39,
                    85
                ],
                [
                    38,
                    85
                ],
                [
                    36,
                    85
                ],
                [
                    36,
                    83
                ],
                [
                    34,
                    80
                ],
                [
                    34,
                    78
                ],
                [
                    33,
                    72
                ],
                [
                    32,
                    69
                ],
                [
                    31,
                    67
                ],
                [
                    31,
                    64
                ],
                [
                    29,
                    62
                ],
                [
                    30,
                    60
                ],
                [
                    30,
                    58
                ],
                [
                    29,
                    57
                ],
                [
                    29,
                    55
                ],
                [
                    30,
                    55
                ]
            ],
            "group_id": null,
            "description": "",
            "shape_type": "polygon",
            "flags": {},
            "mask": null
        }
    ],
    "imagePath": "IMG001128.jpg",
    "imageData": null,
    "imageHeight": 224,
    "imageWidth": 224
}