{
    "version": "5.4.1",
    "flags": {},
    "shapes": [
        {
            "label": "other mt",
            "points": [
                [
                    87,
                    39
                ],
                [
                    141,
                    120
                ]
            ],
            "group_id": null,
            "description": "",
            "shape_type": "rectangle",
            "flags": {},
            "mask": null
        },
        {
            "label": "other mt",
            "points": [
                [
                    131,
                    42
                ],
                [
                    120,
                    41
                ],
                [
                    113,
                    40
                ],
                [
                    106,
                    40
                ],
                [
                    99,
                    42
                ],
                [
                    91,
                    54
                ],
                [
                    91,
                    60
                ],
                [
                    88,
                    83
                ],
                [
                    88,
                    88
                ],
                [
                    88,
                    94
                ],
                [
                    88,
                    110
                ],
                [
                    91,
                    113
                ],
                [
                    95,
                    116
                ],
                [
                    101,
                    118
                ],
                [
                    105,
                    118
                ],
                [
                    115,
                    118
                ],
                [
                    123,
                    116
                ],
                [
                    134,
                    109
                ],
                [
                    140,
                    106
                ],
                [
                    140,
                    77
                ],
                [
                    140,
                    58
                ],
                [
                    138,
                    49
                ],
                [
                    135,
                    43
                ]
            ],
            "group_id": null,
            "description": "",
            "shape_type": "polygon",
            "flags": {},
            "mask": null
        }
    ],
    "imagePath": "IMG001865.jpg",
    "imageData": null,
    "imageHeight": 224,
    "imageWidth": 224
}