{
    "version": "5.4.1",
    "flags": {},
    "shapes": [
        {
            "label": "osteochondroma",
            "points": [
                [
                    84,
                    111
                ],
                [
                    108,
                    132
                ]
            ],
            "group_id": null,
            "description": "",
            "shape_type": "rectangle",
            "flags": {},
            "mask": null
        },
        {
            "label": "osteochondroma",
            "points": [
                [
                    86,
                    125
                ],
                [
                    85,
                    123
                ],
                [
                    85,
                    121
                ],
                [
                    85,
                    118
                ],
                [
                    85,
                    114
                ],
                [
                    86,
                    112
                ],
                [
                    88,
                    112
                ],
                [
                    93,
                    111
                ],
                [
                    99,
                    112
                ],
                [
                    103,
                    112
                ],
                [
                    105,
                    113
                ],
                [
                    107,
                    115
                ],
                [
                    107,
                    117
                ],
                [
                    107,
                    118
                ],
                [
                    106,
                    120
                ],
                [
                    105,
                    122
                ],
                [
                    104,
                    124
                ],
                [
                    104,
                    125
                ],
                [
                    104,
                    127
                ],
                [
                    104,
                    129
                ],
                [
                    103,
                    130
                ],
                [
                    101,
                    131
                ],
                [
                    99,
                    131
                ],
                [
                    97,
                    130
                ],
                [
                    96,
                    128
                ],
                [
                    96,
                    127
                ],
                [
                    95,
                    127
                ],
                [
                    94,
                    127
                ],
                [
                    92,
                    128
                ],
                [
                    91,
                    127
                ],
                [
                    89,
                    127
                ],
                [
                    88,
                    126
                ],
                [
                    86,
                    124
                ]
            ],
            "group_id": null,
            "description": "",
            "shape_type": "polygon",
            "flags": {},
            "mask": null
        }
    ],
    "imagePath": "IMG000321.jpg",
    "imageData": null,
    "imageHeight": 224,
    "imageWidth": 224
}