{
    "version": "5.4.1",
    "flags": {},
    "shapes": [
        {
            "label": "multiple osteochondromas",
            "points": [
                [
                    89,
                    56
                ],
                [
                    142,
                    115
                ]
            ],
            "group_id": null,
            "description": "",
            "shape_type": "rectangle",
            "flags": {},
            "mask": null
        },
        {
            "label": "multiple osteochondromas",
            "points": [
                [
                    103,
                    137
                ],
                [
                    152,
                    168
                ]
            ],
            "group_id": null,
            "description": "",
            "shape_type": "rectangle",
            "flags": {},
            "mask": null
        },
        {
            "label": "multiple osteochondromas",
            "points": [
                [
                    104,
                    58
                ],
                [
                    101,
                    60
                ],
                [
                    100,
                    61
                ],
                [
                    98,
                    62
                ],
                [
                    96,
                    62
                ],
                [
                    93,
                    66
                ],
                [
                    92,
                    71
                ],
                [
                    91,
                    74
                ],
                [
                    90,
                    79
                ],
                [
                    91,
                    83
                ],
                [
                    90,
                    88
                ],
                [
                    90,
                    92
                ],
                [
                    92,
                    95
                ],
                [
                    93,
                    97
                ],
                [
                    94,
                    99
                ],
                [
                    95,
                    101
                ],
                [
                    95,
                    103
                ],
                [
                    96,
                    106
                ],
                [
                    97,
                    107
                ],
                [
                    98,
                    108
                ],
                [
                    115,
                    113
                ],
                [
                    122,
                    113
                ],
                [
                    126,
                    113
                ],
                [
                    128,
                    112
                ],
                [
                    133,
                    108
                ],
                [
                    136,
                    106
                ],
                [
                    140,
                    101
                ],
                [
                    141,
                    94
                ],
                [
                    142,
                    91
                ],
                [
                    141,
                    85
                ],
                [
                    139,
                    80
                ],
                [
                    137,
                    75
                ],
                [
                    135,
                    74
                ],
                [
                    132,
                    71
                ],
                [
                    130,
                    69
                ],
                [
                    128,
                    64
                ],
                [
                    126,
                    60
                ],
                [
                    123,
                    59
                ]
            ],
            "group_id": null,
            "description": "",
            "shape_type": "polygon",
            "flags": {},
            "mask": null
        },
        {
            "label": "multiple osteochondromas",
            "points": [
                [
                    140,
                    138
                ],
                [
                    117,
                    142
                ],
                [
                    107,
                    147
                ],
                [
                    105,
                    152
                ],
                [
                    105,
                    154
                ],
                [
                    106,
                    157
                ],
                [
                    108,
                    160
                ],
                [
                    112,
                    163
                ],
                [
                    117,
                    167
                ],
                [
                    121,
                    165
                ],
                [
                    125,
                    164
                ],
                [
                    129,
                    163
                ],
                [
                    133,
                    165
                ],
                [
                    139,
                    167
                ],
                [
                    143,
                    168
                ],
                [
                    144,
                    168
                ],
                [
                    151,
                    168
                ],
                [
                    151,
                    164
                ],
                [
                    152,
                    160
                ],
                [
                    151,
                    154
                ],
                [
                    149,
                    150
                ],
                [
                    148,
                    147
                ],
                [
                    149,
                    147
                ],
                [
                    151,
                    149
                ],
                [
                    152,
                    148
                ],
                [
                    151,
                    146
                ],
                [
                    149,
                    145
                ],
                [
                    149,
                    145
                ],
                [
                    149,
                    141
                ],
                [
                    150,
                    138
                ],
                [
                    149,
                    138
                ],
                [
                    147,
                    137
                ],
                [
                    145,
                    137
                ],
                [
                    143,
                    137
                ],
                [
                    142,
                    138
                ]
            ],
            "group_id": null,
            "description": "",
            "shape_type": "polygon",
            "flags": {},
            "mask": null
        }
    ],
    "imagePath": "IMG000477.jpg",
    "imageData": null,
    "imageHeight": 224,
    "imageWidth": 224
}